payarc/__init__.py
payarc/payarc.py
payarc-1.7.9.dist-info/LICENSE
payarc-1.7.9.dist-info/METADATA
payarc-1.7.9.dist-info/WHEEL
payarc-1.7.9.dist-info/top_level.txt
payarc-1.7.9.dist-info/RECORD
