Metadata-Version: 2.1
Name: payarc
Version: 1.7.9
Summary: Payarc Python SDK
Home-page: https://github.com/Payarc/payarc-sdk-python
Author: Payarc
Author-email: Spas Tomov <spas@payarc.com>
License: MIT License
Project-URL: repository, https://github.com/Payarc/payarc-sdk-python
Classifier: Development Status :: 3 - Alpha
Classifier: Intended Audience :: Developers
Classifier: Topic :: Software Development :: Build Tools
Classifier: License :: OSI Approved :: MIT License
Classifier: Programming Language :: Python :: 3.8
Requires-Python: >=3.7, <4
License-File: LICENSE
Requires-Dist: httpx
Requires-Dist: asyncio
